bistad_distributions-3.11.dist-info/DESCRIPTION.rst
bistad_distributions-3.11.dist-info/METADATA
bistad_distributions-3.11.dist-info/RECORD
bistad_distributions-3.11.dist-info/WHEEL
bistad_distributions-3.11.dist-info/metadata.json
bistad_distributions-3.11.dist-info/top_level.txt
distributions/Binomialdistribution.py
distributions/Gaussiandistribution.py
distributions/Generaldistribution.py
distributions/__init__.py
